feffery_antd_components/AntdAccordion.py
feffery_antd_components/AntdAffix.py
feffery_antd_components/AntdAlert.py
feffery_antd_components/AntdAnchor.py
feffery_antd_components/AntdAvatar.py
feffery_antd_components/AntdAvatarGroup.py
feffery_antd_components/AntdBackTop.py
feffery_antd_components/AntdBadge.py
feffery_antd_components/AntdBreadcrumb.py
feffery_antd_components/AntdButton.py
feffery_antd_components/AntdCalendar.py
feffery_antd_components/AntdCard.py
feffery_antd_components/AntdCardGrid.py
feffery_antd_components/AntdCardMeta.py
feffery_antd_components/AntdCarousel.py
feffery_antd_components/AntdCascader.py
feffery_antd_components/AntdCenter.py
feffery_antd_components/AntdCheckCard.py
feffery_antd_components/AntdCheckCardGroup.py
feffery_antd_components/AntdCheckableTag.py
feffery_antd_components/AntdCheckbox.py
feffery_antd_components/AntdCheckboxGroup.py
feffery_antd_components/AntdCol.py
feffery_antd_components/AntdCollapse.py
feffery_antd_components/AntdColorPicker.py
feffery_antd_components/AntdComment.py
feffery_antd_components/AntdCompact.py
feffery_antd_components/AntdConfigProvider.py
feffery_antd_components/AntdContent.py
feffery_antd_components/AntdCopyText.py
feffery_antd_components/AntdCountdown.py
feffery_antd_components/AntdCountup.py
feffery_antd_components/AntdCustomSkeleton.py
feffery_antd_components/AntdDatePicker.py
feffery_antd_components/AntdDateRangePicker.py
feffery_antd_components/AntdDescriptionItem.py
feffery_antd_components/AntdDescriptions.py
feffery_antd_components/AntdDivider.py
feffery_antd_components/AntdDraggerUpload.py
feffery_antd_components/AntdDrawer.py
feffery_antd_components/AntdDropdown.py
feffery_antd_components/AntdEmpty.py
feffery_antd_components/AntdFlex.py
feffery_antd_components/AntdFloatButton.py
feffery_antd_components/AntdFloatButtonGroup.py
feffery_antd_components/AntdFooter.py
feffery_antd_components/AntdForm.py
feffery_antd_components/AntdFormItem.py
feffery_antd_components/AntdFormRender.py
feffery_antd_components-0.4.2.dist-info/licenses/LICENSE
feffery_antd_components-0.4.2.dist-info/METADATA
feffery_antd_components-0.4.2.dist-info/WHEEL
feffery_antd_components-0.4.2.dist-info/top_level.txt
feffery_antd_components-0.4.2.dist-info/RECORD
